odoo/addons/base_sparse_field_list_support/README.rst
odoo/addons/base_sparse_field_list_support/__init__.py
odoo/addons/base_sparse_field_list_support/__manifest__.py
odoo/addons/base_sparse_field_list_support/i18n/base_sparse_field_list_support.pot
odoo/addons/base_sparse_field_list_support/models/__init__.py
odoo/addons/base_sparse_field_list_support/models/fields.py
odoo12_addon_base_sparse_field_list_support-12.0.1.0.0.99.dev4.dist-info/METADATA
odoo12_addon_base_sparse_field_list_support-12.0.1.0.0.99.dev4.dist-info/WHEEL
odoo12_addon_base_sparse_field_list_support-12.0.1.0.0.99.dev4.dist-info/top_level.txt
odoo12_addon_base_sparse_field_list_support-12.0.1.0.0.99.dev4.dist-info/RECORD
