Metadata-Version: 2.1
Name: odoo12-addon-base-sparse-field-list-support
Version: 12.0.1.0.0.99.dev4
Summary: add list support to convert_to_cache()
Home-page: https://github.com/shopinvader/odoo-misc
Author: Akretion
License: AGPL-3
Platform: UNKNOWN
Classifier: Programming Language :: Python
Classifier: Framework :: Odoo
Classifier: License :: OSI Approved :: GNU Affero General Public License v3
Requires-Python: >=3.5
Requires-Dist: odoo (<12.1dev,>=12.0a)
